serializer/__init__.py
serializer/__main__.py
serializer/constants.py
serializer/factory/__init__.py
serializer/factory/factory.py
serializer/factory/parsers/__init__.py
serializer/factory/parsers/constants.py
serializer/factory/parsers/parser.py
serializer/factory/parsers/json/__init__.py
serializer/factory/parsers/json/parser.py
serializer/factory/parsers/xml/__init__.py
serializer/factory/parsers/xml/parser.py
serializer/serializer/__init__.py
serializer/serializer/deserializer.py
serializer/serializer/serializer.py
vadvergasov_serialization-1.1.0.dist-info/LICENSE
vadvergasov_serialization-1.1.0.dist-info/METADATA
vadvergasov_serialization-1.1.0.dist-info/WHEEL
vadvergasov_serialization-1.1.0.dist-info/top_level.txt
vadvergasov_serialization-1.1.0.dist-info/RECORD
